lan_file/__init__.py
lan_file/file_utils.py
lan_file/main.py
lan_file/net.py
lan_file/templates/upload.html
lan_file-0.0.5.dist-info/entry_points.txt
lan_file-0.0.5.dist-info/LICENSE
lan_file-0.0.5.dist-info/METADATA
lan_file-0.0.5.dist-info/WHEEL
lan_file-0.0.5.dist-info/RECORD
